pydantic_jsonapi/__init__.py
pydantic_jsonapi/errors.py
pydantic_jsonapi/factory.py
pydantic_jsonapi/filter.py
pydantic_jsonapi/relationships.py
pydantic_jsonapi/request.py
pydantic_jsonapi/resource_identifier.py
pydantic_jsonapi/resource_linkage.py
pydantic_jsonapi/resource_links.py
pydantic_jsonapi/response.py
pydantic_jsonapi-0.10.0.dist-info/LICENSE
pydantic_jsonapi-0.10.0.dist-info/METADATA
pydantic_jsonapi-0.10.0.dist-info/WHEEL
pydantic_jsonapi-0.10.0.dist-info/top_level.txt
pydantic_jsonapi-0.10.0.dist-info/RECORD
