Metadata-Version: 2.1
Name: pydantic-jsonapi
Version: 0.10.0
Summary: an implementation of JSON:api using pydantic
Home-page: https://github.com/DeanWay/pydantic-jsonapi
Author: Dean Way
License: UNKNOWN
Platform: UNKNOWN
Classifier: Programming Language :: Python :: 3.7
Classifier: License :: OSI Approved :: MIT License
Classifier: Operating System :: OS Independent
Requires-Python: >=3.7
Requires-Dist: pydantic (>=0.32.2)
Requires-Dist: typing-extensions (>=3.7.4)
